{
   "dataCryme":[
{"CrimeID": "7a3f30139d4ded899ee7594c72354937962d874baa16597fdffa04e05adb0d81", "Month": "2020-04", "ReportedBy": "Avon and Somerset Constabulary", "FallsWithin": "Avon and Somerset Constabulary", "Longitude": "-3.187863", "Latitude": "54.948226", "Location": " near Field View", "LSOACode": "E01019107", "LSOAName": "Allerdale 002B", "CrimeType": "Violence and sexual offences", "LastOutcomeCategory": "Under investigation", "Context": ";"},
{"CrimeID": "", "Month": "2020-04", "ReportedBy": "Avon and Somerset Constabulary", "FallsWithin": "Avon and Somerset Constabulary", "Longitude": "-2.495055", "Latitude": "51.422132", "Location": " near Cross Street", "LSOACode": "E01014399", "LSOAName": "Bath and North East Somerset 001A", "CrimeType": "Anti-social behaviour", "LastOutcomeCategory": "", "Context": ";"},
{"CrimeID": "6bbecdd3f95444bd8c667972e033b2d469e2d8ad17d707e0813a07ad4a003ce3", "Month": "2020-04", "ReportedBy": "Avon and Somerset Constabulary", "FallsWithin": "Avon and Somerset Constabulary", "Longitude": "-2.509384", "Latitude": "51.409590", "Location": " near Barnard Walk", "LSOACode": "E01014399", "LSOAName": "Bath and North East Somerset 001A", "CrimeType": "Public order", "LastOutcomeCategory": "Under investigation", "Context": ";"},
{"CrimeID": "2972bac2d8979e32b3c10a901db994546a8e823d67afcafc6e2371a03a083b35", "Month": "2020-04", "ReportedBy": "Avon and Somerset Constabulary", "FallsWithin": "Avon and Somerset Constabulary", "Longitude": "-2.509384", "Latitude": "51.409590", "Location": " near Barnard Walk", "LSOACode": "E01014399", "LSOAName": "Bath and North East Somerset 001A", "CrimeType": "Violence and sexual offences", "LastOutcomeCategory": "Under investigation", "Context": ";"},
{"CrimeID": "", "Month": "2020-04", "ReportedBy": "Avon and Somerset Constabulary", "FallsWithin": "Avon and Somerset Constabulary", "Longitude": "-2.497930", "Latitude": "51.417966", "Location": " near Station Road", "LSOACode": "E01014400", "LSOAName": "Bath and North East Somerset 001B", "CrimeType": "Anti-social behaviour", "LastOutcomeCategory": "", "Context": ";"},
{"CrimeID": "", "Month": "2020-04", "ReportedBy": "Avon and Somerset Constabulary", "FallsWithin": "Avon and Somerset Constabulary", "Longitude": "-2.501425", "Latitude": "51.416692", "Location": " near Parking Area", "LSOACode": "E01014400", "LSOAName": "Bath and North East Somerset 001B", "CrimeType": "Anti-social behaviour", "LastOutcomeCategory": "", "Context": ";"},
{"CrimeID": "", "Month": "2020-04", "ReportedBy": "Avon and Somerset Constabulary", "FallsWithin": "Avon and Somerset Constabulary", "Longitude": "-2.503583", "Latitude": "51.418139", "Location": " near Bristol Road", "LSOACode": "E01014400", "LSOAName": "Bath and North East Somerset 001B", "CrimeType": "Anti-social behaviour", "LastOutcomeCategory": "", "Context": ";"},
{"CrimeID": "", "Month": "2020-04", "ReportedBy": "Avon and Somerset Constabulary", "FallsWithin": "Avon and Somerset Constabulary", "Longitude": "-2.500061", "Latitude": "51.414297", "Location": " near Mayfields", "LSOACode": "E01014400", "LSOAName": "Bath and North East Somerset 001B", "CrimeType": "Anti-social behaviour", "LastOutcomeCategory": "", "Context": ";"},
{"CrimeID": "", "Month": "2020-04", "ReportedBy": "Avon and Somerset Constabulary", "FallsWithin": "Avon and Somerset Constabulary", "Longitude": "-2.498613", "Latitude": "51.416002", "Location": " near High Street", "LSOACode": "E01014400", "LSOAName": "Bath and North East Somerset 001B", "CrimeType": "Anti-social behaviour", "LastOutcomeCategory": "", "Context": ";"},
{"CrimeID": "", "Month": "2020-04", "ReportedBy": "Avon and Somerset Constabulary", "FallsWithin": "Avon and Somerset Constabulary", "Longitude": "-2.501425", "Latitude": "51.416692", "Location": " near Parking Area", "LSOACode": "E01014400", "LSOAName": "Bath and North East Somerset 001B", "CrimeType": "Anti-social behaviour", "LastOutcomeCategory": "", "Context": ";"},
{"CrimeID": "", "Month": "2020-04", "ReportedBy": "Avon and Somerset Constabulary", "FallsWithin": "Avon and Somerset Constabulary", "Longitude": "-2.501425", "Latitude": "51.416692", "Location": " near Parking Area", "LSOACode": "E01014400", "LSOAName": "Bath and North East Somerset 001B", "CrimeType": "Anti-social behaviour", "LastOutcomeCategory": "", "Context": ";"},
{"CrimeID": "", "Month": "2020-04", "ReportedBy": "Avon and Somerset Constabulary", "FallsWithin": "Avon and Somerset Constabulary", "Longitude": "-2.499922", "Latitude": "51.417373", "Location": " near Further/Higher Educational Building", "LSOACode": "E01014400", "LSOAName": "Bath and North East Somerset 001B", "CrimeType": "Anti-social behaviour", "LastOutcomeCategory": "", "Context": ";"},
{"CrimeID": "f8ab5d0c3fe967c1cb2b150bae84d9a2eac693d094c704e221b8107c187a0161", "Month": "2020-04", "ReportedBy": "Avon and Somerset Constabulary", "FallsWithin": "Avon and Somerset Constabulary", "Longitude": "-2.510427", "Latitude": "51.423181", "Location": " near Durley Lane", "LSOACode": "E01014400", "LSOAName": "Bath and North East Somerset 001B", "CrimeType": "Criminal damage and arson", "LastOutcomeCategory": "Under investigation", "Context": ";"},
{"CrimeID": "e250d948c8f7e64e7055fa999799ade49aa72418a4ae8e47a9c9abfb72163779", "Month": "2020-04", "ReportedBy": "Avon and Somerset Constabulary", "FallsWithin": "Avon and Somerset Constabulary", "Longitude": "-2.497938", "Latitude": "51.418730", "Location": " near The Avenue", "LSOACode": "E01014400", "LSOAName": "Bath and North East Somerset 001B", "CrimeType": "Criminal damage and arson", "LastOutcomeCategory": "Under investigation", "Context": ";"},
{"CrimeID": "e0acb655baeb78f5008a0241bcd784300424ad707c92db9e76ce4f7ad4dfe418", "Month": "2020-04", "ReportedBy": "Avon and Somerset Constabulary", "FallsWithin": "Avon and Somerset Constabulary", "Longitude": "-2.499922", "Latitude": "51.417373", "Location": " near Further/Higher Educational Building", "LSOACode": "E01014400", "LSOAName": "Bath and North East Somerset 001B", "CrimeType": "Criminal damage and arson", "LastOutcomeCategory": "Under investigation", "Context": ";"},
{"CrimeID": "7ce9d6c2f94d9165d62328801d6b8b682ad51a3d3de698f2299a1e4d370847f8", "Month": "2020-04", "ReportedBy": "Avon and Somerset Constabulary", "FallsWithin": "Avon and Somerset Constabulary", "Longitude": "-2.499922", "Latitude": "51.417373", "Location": " near Further/Higher Educational Building", "LSOACode": "E01014400", "LSOAName": "Bath and North East Somerset 001B", "CrimeType": "Drugs", "LastOutcomeCategory": "Under investigation", "Context": ";"},
{"CrimeID": "cba40540550ee4556249671cd681c82d2aeebf91eb2bd66773f73107eaa9cec6", "Month": "2020-04", "ReportedBy": "Avon and Somerset Constabulary", "FallsWithin": "Avon and Somerset Constabulary", "Longitude": "-2.497930", "Latitude": "51.417966", "Location": " near Station Road", "LSOACode": "E01014400", "LSOAName": "Bath and North East Somerset 001B", "CrimeType": "Other theft", "LastOutcomeCategory": "Under investigation", "Context": ";"},
{"CrimeID": "c1e7346704319fce469084581a2fc41b97d831454adf7ddd041fa2e38572fb3b", "Month": "2020-04", "ReportedBy": "Avon and Somerset Constabulary", "FallsWithin": "Avon and Somerset Constabulary", "Longitude": "-2.496204", "Latitude": "51.417982", "Location": " near Abbey Park", "LSOACode": "E01014400", "LSOAName": "Bath and North East Somerset 001B", "CrimeType": "Public order", "LastOutcomeCategory": "Under investigation", "Context": ";"},
{"CrimeID": "225a70ef21d15970fa541570cc8d44cd7c0b599920e7ae93429c04c73325a209", "Month": "2020-04", "ReportedBy": "Avon and Somerset Constabulary", "FallsWithin": "Avon and Somerset Constabulary", "Longitude": "-2.496204", "Latitude": "51.417982", "Location": " near Abbey Park", "LSOACode": "E01014400", "LSOAName": "Bath and North East Somerset 001B", "CrimeType": "Violence and sexual offences", "LastOutcomeCategory": "Under investigation", "Context": ";"},
{"CrimeID": "c4a16e8fb7fe329849f778cf7e623878326a255f9aebe99934f18c25c39f8202", "Month": "2020-04", "ReportedBy": "Avon and Somerset Constabulary", "FallsWithin": "Avon and Somerset Constabulary", "Longitude": "-2.497767", "Latitude": "51.420232", "Location": " near Chandos Road", "LSOACode": "E01014400", "LSOAName": "Bath and North East Somerset 001B", "CrimeType": "Violence and sexual offences", "LastOutcomeCategory": "Unable to prosecute suspect", "Context": ";"},
{"CrimeID": "6e8b603d42785299e1f147c3f76f86489208d3fb509601b92db79e364108b514", "Month": "2020-04", "ReportedBy": "Avon and Somerset Constabulary", "FallsWithin": "Avon and Somerset Constabulary", "Longitude": "-2.503583", "Latitude": "51.418139", "Location": " near Bristol Road", "LSOACode": "E01014400", "LSOAName": "Bath and North East Somerset 001B", "CrimeType": "Violence and sexual offences", "LastOutcomeCategory": "Under investigation", "Context": ";"},
{"CrimeID": "33c2f54ee07aded01f47f7045ba3153282668bbdecc34c77297710108af4ef67", "Month": "2020-04", "ReportedBy": "Avon and Somerset Constabulary", "FallsWithin": "Avon and Somerset Constabulary", "Longitude": "-2.499922", "Latitude": "51.417373", "Location": " near Further/Higher Educational Building", "LSOACode": "E01014400", "LSOAName": "Bath and North East Somerset 001B", "CrimeType": "Violence and sexual offences", "LastOutcomeCategory": "Under investigation", "Context": ";"},
{"CrimeID": "83c6e2af4b6ac96d20d035180f1e3808f40efea602d9198e741f05e35897d2de", "Month": "2020-04", "ReportedBy": "Avon and Somerset Constabulary", "FallsWithin": "Avon and Somerset Constabulary", "Longitude": "-2.496204", "Latitude": "51.417982", "Location": " near Abbey Park", "LSOACode": "E01014400", "LSOAName": "Bath and North East Somerset 001B", "CrimeType": "Violence and sexual offences", "LastOutcomeCategory": "Under investigation", "Context": ";"},
{"CrimeID": "c82f502bd7a8b93c5956fc753b03ef043d2ae97b8c8c97a2d2b00b22868e30c1", "Month": "2020-04", "ReportedBy": "Avon and Somerset Constabulary", "FallsWithin": "Avon and Somerset Constabulary", "Longitude": "-2.497938", "Latitude": "51.418730", "Location": " near The Avenue", "LSOACode": "E01014400", "LSOAName": "Bath and North East Somerset 001B", "CrimeType": "Violence and sexual offences", "LastOutcomeCategory": "Under investigation", "Context": ";"},
{"CrimeID": "", "Month": "2020-04", "ReportedBy": "Avon and Somerset Constabulary", "FallsWithin": "Avon and Somerset Constabulary", "Longitude": "-2.510393", "Latitude": "51.412355", "Location": " near Cleeve Grove", "LSOACode": "E01014401", "LSOAName": "Bath and North East Somerset 001C", "CrimeType": "Anti-social behaviour", "LastOutcomeCategory": "", "Context": ";"},
{"CrimeID": "", "Month": "2020-04", "ReportedBy": "Avon and Somerset Constabulary", "FallsWithin": "Avon and Somerset Constabulary", "Longitude": "-2.506835", "Latitude": "51.410554", "Location": " near Kelston Road", "LSOACode": "E01014401", "LSOAName": "Bath and North East Somerset 001C", "CrimeType": "Anti-social behaviour", "LastOutcomeCategory": "", "Context": ";"},
{"CrimeID": "", "Month": "2020-04", "ReportedBy": "Avon and Somerset Constabulary", "FallsWithin": "Avon and Somerset Constabulary", "Longitude": "-2.506978", "Latitude": "51.415652", "Location": " near St Margaret'S Close", "LSOACode": "E01014401", "LSOAName": "Bath and North East Somerset 001C", "CrimeType": "Anti-social behaviour", "LastOutcomeCategory": "", "Context": ";"},
{"CrimeID": "", "Month": "2020-04", "ReportedBy": "Avon and Somerset Constabulary", "FallsWithin": "Avon and Somerset Constabulary", "Longitude": "-2.506762", "Latitude": "51.409116", "Location": " near Queens Road", "LSOACode": "E01014401", "LSOAName": "Bath and North East Somerset 001C", "CrimeType": "Anti-social behaviour", "LastOutcomeCategory": "", "Context": ";"},
{"CrimeID": "", "Month": "2020-04", "ReportedBy": "Avon and Somerset Constabulary", "FallsWithin": "Avon and Somerset Constabulary", "Longitude": "-2.506762", "Latitude": "51.409116", "Location": " near Queens Road", "LSOACode": "E01014401", "LSOAName": "Bath and North East Somerset 001C", "CrimeType": "Anti-social behaviour", "LastOutcomeCategory": "", "Context": ";"},
{"CrimeID": "", "Month": "2020-04", "ReportedBy": "Avon and Somerset Constabulary", "FallsWithin": "Avon and Somerset Constabulary", "Longitude": "-2.510393", "Latitude": "51.412355", "Location": " near Cleeve Grove", "LSOACode": "E01014401", "LSOAName": "Bath and North East Somerset 001C", "CrimeType": "Anti-social behaviour", "LastOutcomeCategory": "", "Context": ";"},
{"CrimeID": "7c4e3970c0b00d380fdee5d16c617b297af02415c20d508ee14559b490f38b56", "Month": "2020-04", "ReportedBy": "Avon and Somerset Constabulary", "FallsWithin": "Avon and Somerset Constabulary", "Longitude": "-2.508304", "Latitude": "51.414594", "Location": " near St George'S Road", "LSOACode": "E01014401", "LSOAName": "Bath and North East Somerset 001C", "CrimeType": "Public order", "LastOutcomeCategory": "Under investigation", "Context": ";"},
{"CrimeID": "b850b73cefebfb90c0a0953264350badbdf14c20ad115723fbef03199baa5316", "Month": "2020-04", "ReportedBy": "Avon and Somerset Constabulary", "FallsWithin": "Avon and Somerset Constabulary", "Longitude": "-2.510022", "Latitude": "51.413939", "Location": " near Mendip Close", "LSOACode": "E01014401", "LSOAName": "Bath and North East Somerset 001C", "CrimeType": "Public order", "LastOutcomeCategory": "Unable to prosecute suspect", "Context": ";"},
{"CrimeID": "382ffd3cb644ad03071aac2cb4c1da244b5373cae8a5001ea97649b95559b413", "Month": "2020-04", "ReportedBy": "Avon and Somerset Constabulary", "FallsWithin": "Avon and Somerset Constabulary", "Longitude": "-2.509174", "Latitude": "51.412684", "Location": " near Staple Grove", "LSOACode": "E01014401", "LSOAName": "Bath and North East Somerset 001C", "CrimeType": "Violence and sexual offences", "LastOutcomeCategory": "Unable to prosecute suspect", "Context": ";"},
{"CrimeID": "2a9c142a41c195f7cb062cf068755c53e340ffc7c7767437dc60915c3422b255", "Month": "2020-04", "ReportedBy": "Avon and Somerset Constabulary", "FallsWithin": "Avon and Somerset Constabulary", "Longitude": "-2.505227", "Latitude": "51.415902", "Location": " near St Ladoc Road", "LSOACode": "E01014401", "LSOAName": "Bath and North East Somerset 001C", "CrimeType": "Violence and sexual offences", "LastOutcomeCategory": "Unable to prosecute suspect", "Context": ";"},
{"CrimeID": "17bb07aea9aed412c49ffced5dc97da7fc638b8316831ac4762bdce614b7850a", "Month": "2020-04", "ReportedBy": "Avon and Somerset Constabulary", "FallsWithin": "Avon and Somerset Constabulary", "Longitude": "-2.503079", "Latitude": "51.416757", "Location": " near Culvers Close", "LSOACode": "E01014401", "LSOAName": "Bath and North East Somerset 001C", "CrimeType": "Violence and sexual offences", "LastOutcomeCategory": "Under investigation", "Context": ";"},
{"CrimeID": "961633499ef59f6a820b3853ed334e3bc66fc69c804e57edf668caf695795c18", "Month": "2020-04", "ReportedBy": "Avon and Somerset Constabulary", "FallsWithin": "Avon and Somerset Constabulary", "Longitude": "-2.509174", "Latitude": "51.412684", "Location": " near Staple Grove", "LSOACode": "E01014401", "LSOAName": "Bath and North East Somerset 001C", "CrimeType": "Violence and sexual offences", "LastOutcomeCategory": "Investigation complete; no suspect identified", "Context": ""},
{"CrimeID": "", "Month": "2020-04", "ReportedBy": "Avon and Somerset Constabulary", "FallsWithin": "Avon and Somerset Constabulary", "Longitude": "-2.513006", "Latitude": "51.405591", "Location": " near Holmoak Road", "LSOACode": "E01014402", "LSOAName": "Bath and North East Somerset 002A", "CrimeType": "Anti-social behaviour", "LastOutcomeCategory": "", "Context": ";"},
{"CrimeID": "", "Month": "2020-04", "ReportedBy": "Avon and Somerset Constabulary", "FallsWithin": "Avon and Somerset Constabulary", "Longitude": "-2.514953", "Latitude": "51.404872", "Location": " near Sports/Recreation Area", "LSOACode": "E01014402", "LSOAName": "Bath and North East Somerset 002A", "CrimeType": "Anti-social behaviour", "LastOutcomeCategory": "", "Context": ";"}
]
}